{
  "game": "Rock Band DLC",
  "type": "dlc",
  "compatibility": "rb3_only",
  "year_range": "2008-2009",
  "description": "Released 2008-2009, works in Rock Band 3. Cross-compatible with RB, RB2, RB3 (pre-Oct 2010)",
  "songs": [
    {"title": "Gimme Three Steps", "artist": "Lynyrd Skynyrd", "year": 1973, "genre": "Southern Rock"},
    {"title": "Hard to Handle", "artist": "The Black Crowes", "year": 1990, "genre": "Southern Rock"},
    {"title": "Limelight", "artist": "Rush", "year": 1981, "genre": "Prog"},
    {"title": "Die, All Right!", "artist": "The Hives", "year": 2000, "genre": "Punk"},
    {"title": "Interstate Love Song", "artist": "Stone Temple Pilots", "year": 1994, "genre": "Alternative"},
    {"title": "The Number of the Beast", "artist": "Iron Maiden", "year": 1982, "genre": "Metal"},
    {"title": "Action", "artist": "Sweet", "year": 1976, "genre": "Glam"},
    {"title": "Last Train to Clarksville", "artist": "The Monkees", "year": 1966, "genre": "Pop-Rock"},
    {"title": "All the Small Things", "artist": "Blink-182", "year": 1999, "genre": "Punk"},
    {"title": "Don't Look Back in Anger", "artist": "Oasis", "year": 1995, "genre": "Rock"},
    {"title": "Live Forever", "artist": "Oasis", "year": 1994, "genre": "Rock"},
    {"title": "Wonderwall", "artist": "Oasis", "year": 1995, "genre": "Rock"},
    {"title": "Siva", "artist": "Smashing Pumpkins", "year": 1991, "genre": "Alternative"},
    {"title": "Working Man", "artist": "Rush", "year": 1974, "genre": "Prog"},
    {"title": "Ten Speed", "artist": "Coheed and Cambria", "year": 2005, "genre": "Prog"},
    {"title": "Roam", "artist": "The B-52's", "year": 1989, "genre": "New Wave"},
    {"title": "We Care a Lot", "artist": "Faith No More", "year": 1987, "genre": "Rock"},
    {"title": "Calling Dr. Love", "artist": "Kiss", "year": 1976, "genre": "Classic Rock"},
    {"title": "Complete Control", "artist": "The Clash", "year": 1977, "genre": "Punk"},
    {"title": "Truth Hits Everybody", "artist": "The Police", "year": 1978, "genre": "Rock"},
    {"title": "Teenage Lobotomy", "artist": "Ramones", "year": 1977, "genre": "Punk"},
    {"title": "Sex Type Thing", "artist": "Stone Temple Pilots", "year": 1992, "genre": "Alternative"},
    {"title": "El Scorcho", "artist": "Weezer", "year": 1996, "genre": "Alternative"},
    {"title": "Why Do You Love Me", "artist": "Garbage", "year": 2005, "genre": "Alternative"},
    {"title": "March of the Pigs", "artist": "Nine Inch Nails", "year": 1994, "genre": "Rock"},
    {"title": "The Collector", "artist": "Nine Inch Nails", "year": 2005, "genre": "Rock"},
    {"title": "The Perfect Drug", "artist": "Nine Inch Nails", "year": 1997, "genre": "Rock"},
    {"title": "China Cat Sunflower", "artist": "Grateful Dead", "year": 1969, "genre": "Classic Rock"},
    {"title": "Casey Jones", "artist": "Grateful Dead", "year": 1970, "genre": "Classic Rock"},
    {"title": "Sugar Magnolia", "artist": "Grateful Dead", "year": 1970, "genre": "Classic Rock"},
    {"title": "Truckin'", "artist": "Grateful Dead", "year": 1970, "genre": "Classic Rock"},
    {"title": "Franklin's Tower", "artist": "Grateful Dead", "year": 1975, "genre": "Classic Rock"},
    {"title": "I Need a Miracle", "artist": "Grateful Dead", "year": 1978, "genre": "Classic Rock"},
    {"title": "Crushcrushcrush", "artist": "Paramore", "year": 2007, "genre": "Pop-Rock"},
    {"title": "Beethoven's C***", "artist": "Serj Tankian", "year": 2007, "genre": "Nu-Metal"},
    {"title": "Shockwave", "artist": "Black Tide", "year": 2008, "genre": "Metal"}
  ]
}