{
  "game": "Rock Band DLC",
  "type": "dlc",
  "compatibility": "rb3_rb4",
  "year_range": "2010+",
  "description": "Released 2010 onwards, works in Rock Band 3, Rock Band 4, and later games",
  "songs": [
    {"title": "Band on the Run", "artist": "Paul McCartney", "year": 2009, "genre": "Classic Rock"},
    {"title": "Jet", "artist": "Paul McCartney", "year": 2009, "genre": "Classic Rock"},
    {"title": "Sing the Changes", "artist": "Paul McCartney", "year": 2009, "genre": "Classic Rock"},
    {"title": "Adam's Song", "artist": "Blink-182", "year": 1999, "genre": "Punk"},
    {"title": "First Date", "artist": "Blink-182", "year": 2001, "genre": "Punk"},
    {"title": "I Miss You", "artist": "Blink-182", "year": 2003, "genre": "Punk"},
    {"title": "Love My Way", "artist": "The Psychedelic Furs", "year": 1982, "genre": "New Wave"},
    {"title": "Sister Europe", "artist": "The Psychedelic Furs", "year": 1980, "genre": "New Wave"},
    {"title": "Rock 'n' Roll High School", "artist": "Ramones", "year": 1978, "genre": "Punk"},
    {"title": "Grind", "artist": "Alice in Chains", "year": 1995, "genre": "Grunge"},
    {"title": "Heaven Beside You", "artist": "Alice in Chains", "year": 1995, "genre": "Grunge"},
    {"title": "Last of My Kind", "artist": "Alice in Chains", "year": 2009, "genre": "Grunge"},
    {"title": "We Die Young", "artist": "Alice in Chains", "year": 1990, "genre": "Grunge"},
    {"title": "Your Decision", "artist": "Alice in Chains", "year": 2009, "genre": "Grunge"},
    {"title": "A Woman in Love", "artist": "Tom Petty and the Heartbreakers", "year": 2009, "genre": "Rock"},
    {"title": "Breakdown", "artist": "Tom Petty and the Heartbreakers", "year": 2009, "genre": "Rock"},
    {"title": "Century City", "artist": "Tom Petty and the Heartbreakers", "year": 2009, "genre": "Rock"},
    {"title": "Jammin' Me", "artist": "Tom Petty and the Heartbreakers", "year": 2009, "genre": "Rock"},
    {"title": "Nightwatchman", "artist": "Tom Petty and the Heartbreakers", "year": 2009, "genre": "Rock"},
    {"title": "The Waiting", "artist": "Tom Petty and the Heartbreakers", "year": 2009, "genre": "Rock"},
    {"title": "1901", "artist": "Phoenix", "year": 2009, "genre": "Alternative"},
    {"title": "Lisztomania", "artist": "Phoenix", "year": 2009, "genre": "Alternative"},
    {"title": "Blue Jeans", "artist": "Silvertide", "year": 2004, "genre": "Rock"},
    {"title": "Bulls on Parade", "artist": "Rage Against the Machine", "year": 1996, "genre": "Alternative"},
    {"title": "Hair of the Dog", "artist": "Nazareth", "year": 1975, "genre": "Classic Rock"},
    {"title": "Killed by Death '08", "artist": "Motörhead", "year": 2008, "genre": "Metal"},
    {"title": "Levitate", "artist": "I Mother Earth", "year": 1993, "genre": "Alternative"},
    {"title": "Master of the Universe", "artist": "Hawkwind", "year": 1971, "genre": "Rock"},
    {"title": "Transmaniacon MC", "artist": "Blue Öyster Cult", "year": 1972, "genre": "Classic Rock"},
    {"title": "Godzilla", "artist": "Blue Öyster Cult", "year": 1977, "genre": "Classic Rock"},
    {"title": "Gone", "artist": "Montgomery Gentry", "year": 2004, "genre": "Country"},
    {"title": "Me and My Gang", "artist": "Rascal Flatts", "year": 2006, "genre": "Country"},
    {"title": "On the Road Again", "artist": "Willie Nelson", "year": 1980, "genre": "Country"},
    {"title": "She Thinks My Tractor's Sexy", "artist": "Kenny Chesney", "year": 1999, "genre": "Country"},
    {"title": "Swing", "artist": "Trace Adkins", "year": 2006, "genre": "Country"},
    {"title": "Suds in the Bucket", "artist": "Sara Evans", "year": 2003, "genre": "Country"}
  ]
}